interactiveai/__init__.py
interactiveai/api.py
interactiveai/experiment.py
interactiveai/interactive.py
interactiveai/langchain.py
interactiveai/media.py
interactiveai/model.py
interactiveai/openai.py
interactiveai/types.py
interactiveai-0.0.23.dist-info/licenses/LICENSE.md
interactiveai-0.0.23.dist-info/METADATA
interactiveai-0.0.23.dist-info/WHEEL
interactiveai-0.0.23.dist-info/top_level.txt
interactiveai-0.0.23.dist-info/RECORD
