Metadata-Version: 2.4
Name: interactiveai
Version: 0.0.23
Summary: InteractiveAI client package
Author: InteractiveAI
Project-URL: Homepage, https://interactive.ai
Project-URL: App, https://app.interactive.ai
Classifier: Operating System :: OS Independent
Requires-Python: >=3.8
License-File: LICENSE.md
Requires-Dist: langfuse~=3.5.2
Requires-Dist: langchain-core>=0.3.68
Requires-Dist: loguru>=0.7.0
Dynamic: license-file
